q1/q1.v
module serial_adder(input clk, input reset, input a, input b, input cin, output sum,output cout);
reg sum,cout;
reg c,flag;
always @(posedge clk or posedge reset) begin
    if(reset == 1) begin
        sum = 0;
        cout = c;
        flag = 0;
    end else begin
        if(flag == 0) begin
            c = cin;  
            flag = 1; 
        end 
        cout = 0;
        sum = a ^ b ^ c; 
        c = (a & b) | (c & b) | (a & c);
    end 
end
endmodule

q1/q1_tb.v
`timescale 1ns/1ns
`include "q1.v"
module serial_adder_tb();
 reg clk;
 reg reset;
 reg  a;
 reg b;
 reg cin;
 wire cout;
 wire sum;

 serial_adder S(clk,reset,a,b,cin,sum,cout);

 initial
    begin
        $dumpfile("q1_tb.vcd");
        $dumpvars();
    end
 always 
    #5 clk=~clk;
 initial 
    begin
        clk=0;
        
        reset = 0;
        a = 0;
        b = 0;
        cin = 0;
        reset = 1;  
        #20;
        reset = 0;
        //add two 4 bit numbers, 1011 + 1001 = 10101
        a = 1; b = 1; cin = 1;    #10;
        a = 1; b = 0; cin = 0;  #10;
        a = 0; b = 0; cin = 0;  #10;
        a = 1; b = 1; cin = 0;  #10;
        reset = 1;
        #10;
        reset = 0;
        //add two 5 bit numbers, 11001 + 10011 = 101101
        a = 1; b = 1; cin = 1;    #10;
        a = 0; b = 1; cin = 0;  #10;
        a = 0; b = 0; cin = 0;  #10;
        a = 1; b = 0; cin = 0;  #10;
        a = 1; b = 1; cin = 0;  #10;
        reset = 1;
        #10;

    end
 initial
    begin
        $display("Test Completed!!");
        #140 $finish;
    end
endmodule

q1/q1_tb.vcd
$date
	Sat Dec 24 11:02:01 2022
$end
$version
	Icarus Verilog
$end
$timescale
	1ns
$end
$scope module serial_adder_tb $end
$var wire 1 ! sum $end
$var wire 1 " cout $end
$var reg 1 # a $end
$var reg 1 $ b $end
$var reg 1 % cin $end
$var reg 1 & clk $end
$var reg 1 ' reset $end
$scope module S $end
$var wire 1 # a $end
$var wire 1 $ b $end
$var wire 1 % cin $end
$var wire 1 & clk $end
$var wire 1 ' reset $end
$var reg 1 ( c $end
$var reg 1 " cout $end
$var reg 1 ) flag $end
$var reg 1 ! sum $end
$upscope $end
$upscope $end
$enddefinitions $end
$comment Show the parameter values. $end
$dumpall
$end
#0
$dumpvars
0)
x(
1'
0&
0%
0$
0#
x"
0!
$end
#5
1&
#10
0&
#15
1&
#20
0&
1%
1$
1#
0'
#25
1!
0"
1)
1(
1&
#30
0&
0%
0$
#35
0!
1&
#40
0&
0#
#45
0(
1!
1&
#50
0&
1$
1#
#55
1(
0!
1&
#60
0)
1"
0&
1'
#65
1&
#70
0&
1%
0'
#75
1!
0"
1)
1&
#80
0&
0%
0#
#85
0!
1&
#90
0&
0$
#95
0(
1!
1&
#100
0&
1#
#105
1&
#110
0&
1$
#115
1(
0!
1&
#120
0)
1"
0&
1'
