q2/behavioral_code/q2_a.v
module bsg(input clk,input reset, output [3:0]Q);
reg [3:0] Q;

always@(posedge clk or posedge reset)
 begin
  if(reset==1)
   begin
    Q=0;
   end
  else
   begin
    case(Q)
    0:Q=8;
    8:Q=12;
    12:Q=6;
    6:Q=13;
    13:Q=11;
    11:Q=7;
    7:Q=3;
    3:Q=1;
    1:Q=0;
    endcase
 end

 end

endmodule

q2/behavioral_code/q2_a_tb.v
`timescale 1ns/1ns
`include "q2_a.v"

module bsg_tb();
    reg clk;
    reg reset;
    wire [3:0] Q;

    bsg B(clk,reset,Q);

    initial
    begin
        $dumpfile("behavioural_serial_counter_tb.vcd");
        $dumpvars();
    end

    always
        #10 clk = ~clk;

    initial
    begin
        clk=0;

      reset=1;
      #10;
      reset=0;
      #150;

      reset=1;
      #10;
      reset=0;
      #150;
    end

    initial
    begin
        $display("Test Completed!!");
        #320 $finish;
    end
endmodule

q2/behavioral_code/behavioral_serial_counter_tb.vcd
$date
	Sat Dec 24 11:52:45 2022
$end
$version
	Icarus Verilog
$end
$timescale
	1ns
$end
$scope module bsg_tb $end
$var wire 4 ! Q [3:0] $end
$var reg 1 " clk $end
$var reg 1 # reset $end
$scope module B $end
$var wire 1 " clk $end
$var wire 1 # reset $end
$var reg 4 $ Q [3:0] $end
$upscope $end
$upscope $end
$enddefinitions $end
$comment Show the parameter values. $end
$dumpall
$end
#0
$dumpvars
b0 $
1#
0"
b0 !
$end
#10
b1000 !
b1000 $
0#
1"
#20
0"
#30
b1100 !
b1100 $
1"
#40
0"
#50
b110 !
b110 $
1"
#60
0"
#70
b1101 !
b1101 $
1"
#80
0"
#90
b1011 !
b1011 $
1"
#100
0"
#110
b111 !
b111 $
1"
#120
0"
#130
b11 !
b11 $
1"
#140
0"
#150
b1 !
b1 $
1"
#160
b0 !
b0 $
0"
1#
#170
b1000 !
b1000 $
1"
0#
#180
0"
#190
b1100 !
b1100 $
1"
#200
0"
#210
b110 !
b110 $
1"
#220
0"
#230
b1101 !
b1101 $
1"
#240
0"
#250
b1011 !
b1011 $
1"
#260
0"
#270
b111 !
b111 $
1"
#280
0"
#290
b11 !
b11 $
1"
#300
0"
#310
b1 !
b1 $
1"
