q3/q3_b.v
module seq_detector (input clk, input reset, input in, output out);
  reg [4:0] shift_reg;
  reg out;

  always @(posedge clk) begin
    if (reset) begin
      shift_reg <= 5'b0;
      out <= 1'b0;
    end else begin
      shift_reg <= {shift_reg[3:0], in};
      out <= (shift_reg == 5'b01101);
    end
  end
endmodule

q3/q3_b_tb.v
`timescale 1ns / 1ns
`include "q3_b.v"

module seq_detector_tb;
  reg clk;
  reg reset;
  reg in;
  wire out;

  seq_detector s1 (clk, reset, in, out);

  always #5 clk = ~clk;
  initial
    begin
     $dumpfile("with_overlap.vcd");
     $dumpvars();
    end
   
  initial begin
    clk = 0;
    in=0;
    reset = 1;#10;
    reset = 0;#10;
    in = 1;#10;
    in = 0;#10;
    in = 1;#10;
    in = 0;#10;
    in = 1;#10;
    in = 1;#10;
    in = 0;#10;
    in = 1;#10;
    in = 1;#10;
    in = 0;#10;
    in = 1;#10;
  end

  initial 
   begin
    $display("Test Completed!");
    #140 $finish;
   end
endmodule

q3/with_overlap.vcd
$date
	Sat Dec 24 14:01:49 2022
$end
$version
	Icarus Verilog
$end
$timescale
	1ns
$end
$scope module seq_detector_tb $end
$var wire 1 ! out $end
$var reg 1 " clk $end
$var reg 1 # in $end
$var reg 1 $ reset $end
$scope module s1 $end
$var wire 1 " clk $end
$var wire 1 # in $end
$var wire 1 $ reset $end
$var reg 1 ! out $end
$var reg 5 % shift_reg [4:0] $end
$upscope $end
$upscope $end
$enddefinitions $end
$comment Show the parameter values. $end
$dumpall
$end
#0
$dumpvars
bx %
1$
0#
0"
x!
$end
#5
0!
b0 %
1"
#10
0"
0$
#15
1"
#20
0"
1#
#25
b1 %
1"
#30
0"
0#
#35
b10 %
1"
#40
0"
1#
#45
b101 %
1"
#50
0"
0#
#55
b1010 %
1"
#60
0"
1#
#65
b10101 %
1"
#70
0"
#75
b1011 %
1"
#80
0"
0#
#85
b10110 %
1"
#90
0"
1#
#95
b1101 %
1"
#100
0"
#105
1!
b11011 %
1"
#110
0"
0#
#115
0!
b10110 %
1"
#120
0"
1#
#125
b1101 %
1"
#130
0"
#135
1!
b11011 %
1"
