q4/q4_a/q4_a.v
module lfsr (input clk, input reset, output reg [2:0] Q, input[2:0] load);
  reg flag;
  always @(posedge clk or posedge reset) begin
    if (reset) begin
      Q <= 3'b000;
      flag=0;
    end else begin
      if(flag==0)
      begin
        Q=load;
        flag=1;
      end
      Q <= {Q[0] ^ Q[1], Q[2], Q[1]};
    end
  end
endmodule

q4/q4_a/q4_a_tb.v
`timescale 1ns/1ns
`include "q4_a.v"

module lfsr_tb();
  reg clk;
  reg reset;
  reg [2:0] load;
  wire [2:0] q;

  lfsr L (clk, reset, q, load);
  always #5 clk=~clk;

  initial
    begin
     $dumpfile("behavioral_lfsr.vcd");
     $dumpvars();
    end

  initial begin
    clk = 0;
    load=3'b111;
    reset = 1;
    #10;
    reset = 0;
    end
  initial begin
    $display("Test completed!");
   #100 $finish;
  end
endmodule

q4/q4_a/behavioral_lfsr.vcd
$date
	Sat Dec 24 16:10:51 2022
$end
$version
	Icarus Verilog
$end
$timescale
	1ns
$end
$scope module lfsr_tb $end
$var wire 3 ! q [2:0] $end
$var reg 1 " clk $end
$var reg 3 # load [2:0] $end
$var reg 1 $ reset $end
$scope module L $end
$var wire 1 " clk $end
$var wire 3 % load [2:0] $end
$var wire 1 $ reset $end
$var reg 3 & Q [2:0] $end
$var reg 1 ' flag $end
$upscope $end
$upscope $end
$enddefinitions $end
$comment Show the parameter values. $end
$dumpall
$end
#0
$dumpvars
0'
b0 &
b111 %
1$
b111 #
0"
b0 !
$end
#5
1"
#10
0"
0$
#15
1'
b11 !
b11 &
1"
#20
0"
#25
b1 !
b1 &
1"
#30
0"
#35
b100 !
b100 &
1"
#40
0"
#45
b10 !
b10 &
1"
#50
0"
#55
b101 !
b101 &
1"
#60
0"
#65
b110 !
b110 &
1"
#70
0"
#75
b111 !
b111 &
1"
#80
0"
#85
b11 !
b11 &
1"
#90
0"
#95
b1 !
b1 &
1"
