q2/structural_code/mux.v
module mux (I3,I2,I1,I0,S1,S0,Y);

    input I3,I2,I1,I0;
    input S1,S0;

    output Y;

    assign Y = S1 ? (S0 ? I3 : I2) : (S0 ? I1 : I0);

endmodule

q2/structural_code/dff.v
module dff(clk,D,Q,_Q,clr,pr);
input clk;
input D;
input clr;
input pr;

output reg Q;
output reg _Q;

always @(posedge clk,pr,clr)
begin
if(pr)
begin
Q<=1;
_Q<=0;
end
else if(clr)
begin
Q<=0;
_Q<=1;
end
else
begin
 Q<=D;
_Q<=~D;
end
    end
endmodule

q2/structural_code/shift_register.v
`include "dff.v"
`include "mux.v"
module shift_register(input clk, input clr, input S1,input S0,input SIL,input SIR, input [3:0] P, output [3:0] Q);
wire y3,y2,y1,y0;
wire [3:0] _Q;

not(_Q[3],Q[3]);
not(_Q[2],Q[2]);
not(_Q[1],Q[1]);
not(_Q[0],Q[0]); 

dff d3(clk,y3,Q[3],_Q[3],clr,1'b0);
dff d2(clk,y2,Q[2],_Q[2],clr,1'b0);
dff d1(clk,y1,Q[1],_Q[1],clr,1'b0);
dff d0(clk,y0,Q[0],_Q[0],clr,1'b0);

mux m3(P[3],Q[2],SIR,Q[3],S1,S0,y3);
mux m2(P[2],Q[1],Q[3],Q[2],S1,S0,y2);
mux m1(P[1],Q[0],Q[2],Q[1],S1,S0,y1);
mux m0(P[0],SIL,Q[1],Q[0],S1,S0,y0);
endmodule

q2/structural_code/q2_b.v
`include "shift_register.v"
module ssg(input clk, input reset, output [3:0] Q);
wire p1, p2, p3, p4, p5, SIR, SIL, S1,S0;
not(p1,Q[0]);
and(p2,p1,Q[1]);
nor(p3,Q[2],Q[1],Q[0]);
and(p4,Q[0],Q[3]);
or(p5,p4,p2);
assign SIR=p3;
assign SIL=p5;
assign S1=p5;
not(S0,p5);
shift_register SR(clk,reset,S1,S0,SIL,SIR,4'b0000,Q);
endmodule

q2/structural_code/q2_b_tb.v
`timescale 1ns/1ns
`include "q2_b.v"

module ssg_tb();
    reg clk;
    reg reset;
    wire [3:0] Q;

    ssg S1(clk,reset,Q);

    initial
    begin
        $dumpfile("structural_serial_counter_tb.vcd");
        $dumpvars();
    end

    always
        #10 clk = ~clk;

    initial
    begin
        clk=0;

      reset=1;
      #10;
      reset=0;
      #150;

      reset=1;
      #10;
      reset=0;
      #150;
    end

    initial
    begin
        $display("Test Completed!!");
        #320 $finish;
    end
endmodule

q2/structural_code/structural_serial_counter_tb.vcd
$date
	Sat Dec 24 12:49:10 2022
$end
$version
	Icarus Verilog
$end
$timescale
	1ns
$end
$scope module ssg_tb $end
$var wire 4 ! Q [3:0] $end
$var reg 1 " clk $end
$var reg 1 # reset $end
$scope module S1 $end
$var wire 1 $ S0 $end
$var wire 1 % S1 $end
$var wire 1 & SIL $end
$var wire 1 ' SIR $end
$var wire 1 " clk $end
$var wire 1 ( p1 $end
$var wire 1 ) p2 $end
$var wire 1 * p3 $end
$var wire 1 + p4 $end
$var wire 1 , p5 $end
$var wire 1 # reset $end
$var wire 4 - Q [3:0] $end
$scope module SR $end
$var wire 4 . P [3:0] $end
$var wire 1 $ S0 $end
$var wire 1 % S1 $end
$var wire 1 & SIL $end
$var wire 1 ' SIR $end
$var wire 4 / _Q [3:0] $end
$var wire 1 " clk $end
$var wire 1 # clr $end
$var wire 1 0 y3 $end
$var wire 1 1 y2 $end
$var wire 1 2 y1 $end
$var wire 1 3 y0 $end
$var wire 4 4 Q [3:0] $end
$scope module d0 $end
$var wire 1 " clk $end
$var wire 1 # clr $end
$var wire 1 5 pr $end
$var wire 1 3 D $end
$var reg 1 6 Q $end
$var reg 1 7 _Q $end
$upscope $end
$scope module d1 $end
$var wire 1 " clk $end
$var wire 1 # clr $end
$var wire 1 8 pr $end
$var wire 1 2 D $end
$var reg 1 9 Q $end
$var reg 1 : _Q $end
$upscope $end
$scope module d2 $end
$var wire 1 " clk $end
$var wire 1 # clr $end
$var wire 1 ; pr $end
$var wire 1 1 D $end
$var reg 1 < Q $end
$var reg 1 = _Q $end
$upscope $end
$scope module d3 $end
$var wire 1 " clk $end
$var wire 1 # clr $end
$var wire 1 > pr $end
$var wire 1 0 D $end
$var reg 1 ? Q $end
$var reg 1 @ _Q $end
$upscope $end
$scope module m0 $end
$var wire 1 A I0 $end
$var wire 1 B I1 $end
$var wire 1 & I2 $end
$var wire 1 C I3 $end
$var wire 1 $ S0 $end
$var wire 1 % S1 $end
$var wire 1 3 Y $end
$upscope $end
$scope module m1 $end
$var wire 1 D I0 $end
$var wire 1 E I1 $end
$var wire 1 F I2 $end
$var wire 1 G I3 $end
$var wire 1 $ S0 $end
$var wire 1 % S1 $end
$var wire 1 2 Y $end
$upscope $end
$scope module m2 $end
$var wire 1 H I0 $end
$var wire 1 I I1 $end
$var wire 1 J I2 $end
$var wire 1 K I3 $end
$var wire 1 $ S0 $end
$var wire 1 % S1 $end
$var wire 1 1 Y $end
$upscope $end
$scope module m3 $end
$var wire 1 L I0 $end
$var wire 1 ' I1 $end
$var wire 1 M I2 $end
$var wire 1 N I3 $end
$var wire 1 $ S0 $end
$var wire 1 % S1 $end
$var wire 1 0 Y $end
$upscope $end
$upscope $end
$upscope $end
$upscope $end
$enddefinitions $end
$comment Show the parameter values. $end
$dumpall
$end
#0
$dumpvars
0N
0M
0L
0K
0J
0I
0H
0G
0F
0E
0D
0C
0B
0A
1@
0?
0>
1=
0<
0;
1:
09
08
17
06
05
b0 4
03
02
01
10
b1111 /
b0 .
b0 -
0,
0+
1*
0)
1(
1'
0&
0%
1$
1#
0"
b0 !
$end
#10
11
1L
1I
b111 /
0@
b1000 !
b1000 -
b1000 4
1?
0#
1"
#20
0"
#30
00
12
0'
0*
1M
1H
1E
b11 /
0=
b1100 !
b1100 -
b1100 4
1<
1"
#40
0"
#50
13
10
02
0$
1&
1%
1,
11
1)
1J
1D
1B
0L
0I
0:
19
b1001 /
1@
b110 !
b110 -
b110 4
0?
1"
#60
0"
#70
12
01
0(
0)
1+
1F
1A
0J
0D
0B
1L
1I
07
16
1:
09
b10 /
0@
b1101 !
b1101 -
b1101 4
1?
1"
#80
0"
#90
11
00
1J
1D
1B
0M
0H
0E
0:
19
b100 /
1=
b1011 !
b1011 -
b1011 4
0<
1"
#100
0"
#110
01
1$
0&
0%
0,
0+
1M
1H
1E
0L
0I
0=
1<
b1000 /
1@
b111 !
b111 -
b111 4
0?
1"
#120
0"
#130
02
0M
0H
0E
b1100 /
1=
b11 !
b11 -
b11 4
0<
1"
#140
0"
#150
03
0J
0D
0B
b1110 /
1:
b1 !
b1 -
b1 4
09
1"
#160
10
1'
1*
1(
0F
0A
b1111 /
17
b0 !
b0 -
b0 4
06
0"
1#
#170
11
1L
1I
b111 /
0@
b1000 !
b1000 -
b1000 4
1?
1"
0#
#180
0"
#190
00
12
0'
0*
1M
1H
1E
b11 /
0=
b1100 !
b1100 -
b1100 4
1<
1"
#200
0"
#210
13
10
02
0$
1&
1%
1,
11
1)
1J
1D
1B
0L
0I
0:
19
b1001 /
1@
b110 !
b110 -
b110 4
0?
1"
#220
0"
#230
12
01
0(
0)
1+
1F
1A
0J
0D
0B
1L
1I
07
16
1:
09
b10 /
0@
b1101 !
b1101 -
b1101 4
1?
1"
#240
0"
#250
11
00
1J
1D
1B
0M
0H
0E
0:
19
b100 /
1=
b1011 !
b1011 -
b1011 4
0<
1"
#260
0"
#270
01
1$
0&
0%
0,
0+
1M
1H
1E
0L
0I
0=
1<
b1000 /
1@
b111 !
b111 -
b111 4
0?
1"
#280
0"
#290
02
0M
0H
0E
b1100 /
1=
b11 !
b11 -
b11 4
0<
1"
#300
0"
#310
03
0J
0D
0B
b1110 /
1:
b1 !
b1 -
b1 4
09
1"
